COPYING.md
MANIFEST.in
README.md
setup.py
bdfu/__init__.py
bdfu/auth.py
bdfu/client.py
bdfu/storage.py
bdfu/tool.py
bdfu/webapp.py
bdfu.egg-info/PKG-INFO
bdfu.egg-info/SOURCES.txt
bdfu.egg-info/dependency_links.txt
bdfu.egg-info/entry_points.txt
bdfu.egg-info/requires.txt
bdfu.egg-info/top_level.txt
examples/make-token.py
examples/simple-server.cfg
examples/simple-server.py
examples/upload.py
examples/cgi-bin/bdfu