Metadata-Version: 1.0
Name: bdfu
Version: 1.0.3
Summary: A "brain dead"-simple file upload server
Home-page: UNKNOWN
Author: UNKNOWN
Author-email: UNKNOWN
License: UNKNOWN
Platform: UNKNOWN
